LICENSE
README.md
setup.cfg
setup.py
opsany.egg-info/PKG-INFO
opsany.egg-info/SOURCES.txt
opsany.egg-info/dependency_links.txt
opsany.egg-info/entry_points.txt
opsany.egg-info/requires.txt
opsany.egg-info/top_level.txt
opsanyctl/__init__.py
opsanyctl/constants.py
opsanyctl/help_content.py
opsanyctl/libs.py
opsanyctl/main.py
opsanyctl/api/__init__.py
opsanyctl/api/base.py
opsanyctl/api/fields.py
opsanyctl/api/resource.py
opsanyctl/api/resource_type.py
tests/__init__.py