Metadata-Version: 2.1
Name: opsany
Version: 0.1.0
Summary: OpsAny's command-line tool!
Author: OpsAny
Author-email: 
Classifier: Programming Language :: Python :: 3.6
Classifier: License :: OSI Approved :: MIT License
Classifier: Operating System :: OS Independent
Requires-Python: >=3.6
License-File: LICENSE
Requires-Dist: typer
Requires-Dist: rich
Requires-Dist: pyyaml
Requires-Dist: requests
